tx.v
module tx(clk1, btn, data, out);
    input clk1;
    input btn;
    input [7:0]data;
    output out;

    reg [2:0]state;
    reg [3:0]bitIndex;
    reg [7:0]dataStore;
    reg o = 1;

    parameter standby = 0, waitRelease = 1, startBit = 2, processBits = 3, endBit = 4;

    always @ (posedge clk1) begin
        case(state)
            // Waiting for input state
            standby: begin
                o <= 1;    // Output is high while idle
                if(~btn) state <= waitRelease;
            end

            // Waiting for button release
            waitRelease: begin
                if(btn) begin
                    dataStore <= data;
                    state <= startBit;
                end
            end

            // Start bit to start getting the data bits
            startBit: begin
                bitIndex <= 0; // Reset index count for processing
                o <= 0;
                state <= processBits;
            end

            // Get bit by bit looping through the indexes
            processBits: begin
                if(bitIndex < 7) begin
                    o <= data[bitIndex];
                    bitIndex <= bitIndex + 1;
                end
                else begin
                    o <= data[bitIndex];
                    state <= endBit;
                end
            end

            // Go back to standby after finishing getting the data bits
            endBit: begin
                o <= 1;
                state <= standby;
            end

            default: begin
                state <= standby;
            end
        endcase
    end

    assign out = o;
endmodule

tx_tb.v
module tx_tb();
    reg clk1, btn;
    reg [7:0]data;
    wire out;

    initial begin
        $dumpfile("tx.vcd");
        $dumpvars(0, tx_tb);
        $display("time   clock     button       data     out");
        $monitor(" %g\t %b\t    %b\t    %b    %b", $time, clk1, btn, data, out);
        clk1 = 1;
        btn = 1;
        data = 0;
        #1 data = 8;
        #2 btn = 0;
        #2 btn = 1;
        // #25 btn = 0;
        // #2 btn = 1;
        #45 $finish;
    end

    always begin
        #1 clk1 = ~clk1;
    end

    tx UUT(clk1, btn, data, out);
endmodule

tx.vcd
$date
	Wed Aug 25 19:00:23 2021
$end
$version
	Icarus Verilog
$end
$timescale
	1s
$end
$scope module tx_tb $end
$var wire 1 ! out $end
$var reg 1 " btn $end
$var reg 1 # clk1 $end
$var reg 8 $ data [7:0] $end
$scope module UUT $end
$var wire 1 " btn $end
$var wire 1 # clk1 $end
$var wire 8 % data [7:0] $end
$var wire 1 ! out $end
$var reg 4 & bitIndex [3:0] $end
$var reg 8 ' dataStore [7:0] $end
$var reg 1 ( o $end
$var reg 3 ) state [2:0] $end
$upscope $end
$upscope $end
$enddefinitions $end
#0
$dumpvars
b0 )
1(
bx '
bx &
b0 %
b0 $
1#
1"
1!
$end
#1
0#
b1000 $
b1000 %
#2
1#
#3
0#
0"
#4
b1 )
1#
#5
0#
1"
#6
b10 )
b1000 '
1#
#7
0#
#8
b11 )
0!
0(
b0 &
1#
#9
0#
#10
b1 &
1#
#11
0#
#12
b10 &
1#
#13
0#
#14
b11 &
1#
#15
0#
#16
b100 &
1!
1(
1#
#17
0#
#18
b101 &
0!
0(
1#
#19
0#
#20
b110 &
1#
#21
0#
#22
b111 &
1#
#23
0#
#24
b100 )
1#
#25
0#
#26
b0 )
1!
1(
1#
