display.v
module display (data, disp1, disp0);
    input [4:0] data;
    output [6:0] disp1;
    output [6:0] disp0;

    reg disp0reg;
    reg disp1reg;
    parameter zero = 7'b0000001;  // "0"
    parameter one = 7'b1001111;  // "1"
    parameter two = 7'b0010010; // "2"
    parameter three = 7'b0000110;  // "3"
    parameter four = 7'b1001100;  // "4"
    parameter five = 7'b0100100; // "5"
    parameter six = 7'b0100000; // "6"
    parameter seven = 7'b0001111; // "7"
    parameter eight= 7'b0000000; // "8"
    parameter nine= 7'b0000100; // "9"
    parameter clr = 7'b1111111; // Clean display

    always @ (*) begin
        case(data)
            5'b00000: begin
                disp1reg <= clr;
                disp0reg <= zero;
            end
            5'b00001: begin
                disp1reg <= clr;
                disp0reg <= one;
            end
            5'b00010: begin
                disp1reg <= clr;
                disp0reg <= two;
            end
            5'b00011: begin
                disp1reg <= clr;
                disp0reg <= three;
            end
            5'b00100: begin
                disp1reg <= clr;
                disp0reg <= four;
            end
            5'b00101: begin
                disp1reg <= clr;
                disp0reg <= five;
            end
            5'b00110: begin
                disp1reg <= clr;
                disp0reg <= six;
            end
            5'b00111: begin
                disp1reg <= clr;
                disp0reg <= seven;
            end
            5'b01000: begin
                disp1reg <= clr;
                disp0reg <= eight;
            end
            5'b01001: begin
                disp1reg <= clr;
                disp0reg <= nine;
            end
            5'b01010: begin
                disp1reg <= one;
                disp0reg <= zero;
            end
            5'b01011: begin
                disp1reg <= one;
                disp0reg <= one;
            end
            5'b01100: begin
                disp1reg <= one;
                disp0reg <= two;
            end
            5'b01101: begin
                disp1reg <= one;
                disp0reg <= three;
            end
            5'b01110: begin
                disp1reg <= one;
                disp0reg <= four;
            end
            5'b01111: begin
                disp1reg <= one;
                disp0reg <= five;
            end
            default: begin
                disp1reg <= clr;
                disp0reg <= clr;
            end
        endcase
    end

    assign disp0 = disp0reg;
    assign disp1 = disp1reg;
endmodule

rx.v
module rx(clk2, transmission, ledData, display);
    input clk2, transmission; // transmission => first 4 are instruction bits, last 4 are the data
    output [0:7]ledData;
    output [0:4]display;
    
    reg [0:7]led_date_placeholder;
    reg [0:4]display_placeholder;
    reg [0:3]dataRecorder; // Registrador de Data
    reg [0:3]dataRegistry;
    reg [0:3]instructionRecorder; // Registrador de Instruction
    reg [0:3]bitIndex = 7; // Index do bit para saber quando para de pegar instrução e data
    reg [0:3]state = 5;
    parameter clean = 1, loadData = 3, storeData = 2, showData = 4, startBit = 5, getInstruction = 6;

    assign ledData = led_date_placeholder;
    assign display = display_placeholder;

    always @(posedge clk2) begin
        case(state)
            startBit: begin
                $display("START - BITINDEX: %d\n", bitIndex);
                if(~transmission) begin
                    state <= loadData;
                end
            end

            loadData: begin
                $display("LOAD - BITINDEX: %d\n", bitIndex);
                if(bitIndex < 4) begin // 7 6 5 4
                    state <= getInstruction;
                end
                else begin
                    if(bitIndex == 4) begin
                        state <= getInstruction;
                    end
                    dataRecorder[bitIndex - 4] <= transmission; // Instruction is after data
                    led_date_placeholder[bitIndex] <= transmission;
                    bitIndex <= bitIndex - 1;
                end
            end

            getInstruction: begin // 3 2 1 0
                $display("GET INSSTR - BITINDEX: %d\n", bitIndex);
                if(bitIndex == 8) begin
                    $display("instructionRecorder: %d\n", instructionRecorder);
                    if(instructionRecorder == 1) begin
                        state <= clean;
                    end
                    else begin 
                        if(instructionRecorder == 4) begin
                            state <= showData;
                        end
                        else begin
                            if(instructionRecorder == 2) begin
                                state <= storeData;
                            end
                            else begin
                            state <= startBit;
                            end
                        end
                    end
                    bitIndex <= 7; // resetar para pegar o próximo transmission
                end
                else begin
                    instructionRecorder[bitIndex] <= transmission; // Instruction is after data
                    led_date_placeholder[bitIndex] <= transmission;
                    
                    if(bitIndex > 0) begin
                        bitIndex <= bitIndex - 1;
                    end
                    else begin 
                        bitIndex <= 8;
                    end
                end
            end

            showData: begin
                $display("SHOW - BITINDEX: %d\n", bitIndex);
                display_placeholder <= dataRegistry;
                state <= startBit;
            end

            storeData: begin
                $display("STORE - BITINDEX: %d\n", bitIndex);
                dataRegistry <= dataRecorder;
                state <= startBit;
            end

            clean: begin
                $display("CLEAN - BITINDEX: %d\n", bitIndex);
                display_placeholder <= 16;
                state <= startBit;
            end
        endcase
    end
endmodule

tx.v
module tx(clk1, btn, data, out);
    input clk1;
    input btn;
    input [7:0]data;
    output out;

    reg [2:0]state;
    reg [3:0]bitIndex;
    reg [7:0]dataStore;
    reg o = 1;

    parameter standby = 0, waitRelease = 1, startBit = 2, processBits = 3, endBit = 4;

    always @ (posedge clk1) begin
        case(state)
            // Waiting for input state
            standby: begin
                o <= 1;    // Output is high while idle
                if(~btn) state <= waitRelease;
            end

            // Waiting for button release
            waitRelease: begin
                if(btn) begin
                    dataStore <= data;
                    state <= startBit;
                end
            end

            // Start bit to start getting the data bits
            startBit: begin
                bitIndex <= 0; // Reset index count for processing
                o <= 0;
                state <= processBits;
            end

            // Get bit by bit looping through the indexes
            processBits: begin
                if(bitIndex < 7) begin
                    o <= data[bitIndex];
                    bitIndex <= bitIndex + 1;
                end
                else begin
                    o <= data[bitIndex];
                    state <= endBit;
                end
            end

            // Go back to standby after finishing getting the data bits
            endBit: begin
                o <= 1;
                state <= standby;
            end

            default: begin
                state <= standby;
            end
        endcase
    end

    assign out = o;
endmodule

uart_tb.v
`timescale 1us/10ns

module uart_tb();
    reg clk1, clk2, btn;
    reg [7:0]data;
    wire [4:0]display;
    wire [7:0]ledData;
    wire transmission;
    wire [6:0]disp1;
    wire [6:0]disp0;

    parameter clockPeriod = 1; // 1 MHz base clock
    parameter clocksPerBit = 53; //How many pulses are needed so transmission is 9600 baud

    initial begin
        $dumpfile("uart.vcd");
        $dumpvars(0, uart_tb);
        clk1 = 1;
        clk2 = 1;
        btn = 1;
        data = 0;
        
        #(clockPeriod * clocksPerBit) data = 20;

        #(clockPeriod * clocksPerBit) btn = 0;

        #(clockPeriod * clocksPerBit) btn = 1;

        #(clockPeriod * clocksPerBit * 100) $finish;
    end

    always begin
        #(clockPeriod * clocksPerBit/2) clk1 = ~clk1;
    end

    always begin
        #(clockPeriod * clocksPerBit/2) clk2 = ~clk2;
    end

    tx tx_UUT(clk1, btn, data, transmission);
    rx rx_UUT(clk2, transmission, ledData, display);
    display display_UUT(display, disp1, disp0);
endmodule

uart.vcd
$date
	Thu Aug 26 21:15:50 2021
$end
$version
	Icarus Verilog
$end
$timescale
	10ns
$end
$scope module uart_tb $end
$var wire 1 ! transmission $end
$var wire 8 " ledData [7:0] $end
$var wire 5 # display [4:0] $end
$var wire 7 $ disp1 [6:0] $end
$var wire 7 % disp0 [6:0] $end
$var reg 1 & btn $end
$var reg 1 ' clk1 $end
$var reg 1 ( clk2 $end
$var reg 8 ) data [7:0] $end
$scope module display_UUT $end
$var wire 7 * disp1 [6:0] $end
$var wire 7 + disp0 [6:0] $end
$var wire 5 , data [4:0] $end
$var reg 1 - disp0reg $end
$var reg 1 . disp1reg $end
$upscope $end
$scope module rx_UUT $end
$var wire 1 ( clk2 $end
$var wire 5 / display [0:4] $end
$var wire 8 0 ledData [0:7] $end
$var wire 1 ! transmission $end
$var reg 4 1 bitIndex [0:3] $end
$var reg 4 2 dataRecorder [0:3] $end
$var reg 4 3 dataRegistry [0:3] $end
$var reg 5 4 display_placeholder [0:4] $end
$var reg 4 5 instructionRecorder [0:3] $end
$var reg 8 6 led_date_placeholder [0:7] $end
$var reg 4 7 state [0:3] $end
$upscope $end
$scope module tx_UUT $end
$var wire 1 & btn $end
$var wire 1 ' clk1 $end
$var wire 8 8 data [7:0] $end
$var wire 1 ! out $end
$var reg 4 9 bitIndex [3:0] $end
$var reg 8 : dataStore [7:0] $end
$var reg 1 ; o $end
$var reg 3 < state [2:0] $end
$upscope $end
$upscope $end
$enddefinitions $end
#0
$dumpvars
b0 <
1;
bx :
bx 9
b0 8
b101 7
bx 6
bx 5
bx 4
bx 3
bx 2
b111 1
bx 0
bx /
x.
x-
bx ,
b0x +
b0x *
b0 )
1(
1'
1&
b0x %
b0x $
bx #
bx "
1!
$end
#2600
0(
0'
#5200
1(
1'
#5300
b10100 )
b10100 8
#7800
0(
0'
#10400
1(
1'
#10600
0&
#13000
0(
0'
#15600
b1 <
1(
1'
#15900
1&
#18200
0(
0'
#20800
b10 <
b10100 :
1(
1'
#23400
0(
0'
#26000
b11 <
0!
0;
b0 9
1(
1'
#28600
0(
0'
#31200
b11 7
b1 9
1(
1'
#33800
0(
0'
#36400
b110 1
bx0 "
bx0 0
bx0 6
bx0 2
b10 9
1(
1'
#39000
0(
0'
#41600
b101 1
bx00 "
bx00 0
bx00 6
bx00 2
b11 9
1!
1;
1(
1'
#44200
0(
0'
#46800
b100 1
bx100 "
bx100 0
bx100 6
bx100 2
b100 9
0!
0;
1(
1'
#49400
0(
0'
#52000
b11 1
bx0100 "
bx0100 0
bx0100 6
b100 2
b110 7
b101 9
1!
1;
1(
1'
#54600
0(
0'
#57200
b10 1
bx10100 "
bx10100 0
bx10100 6
bx1 5
b110 9
0!
0;
1(
1'
#59800
0(
0'
#62400
b1 1
bx010100 "
bx010100 0
bx010100 6
bx01 5
b111 9
1(
1'
#65000
0(
0'
#67600
b0 1
bx0010100 "
bx0010100 0
bx0010100 6
bx001 5
b100 <
1(
1'
#70200
0(
0'
#72800
b1000 1
b10100 "
b10100 0
b10100 6
b1 5
b0 <
1!
1;
1(
1'
#75400
0(
0'
#78000
b111 1
b1 7
1(
1'
#80600
0(
0'
#83200
b1 %
b1 +
1-
b1 $
b1 *
1.
b101 7
b10000 #
b10000 ,
b10000 /
b10000 4
1(
1'
